blif2graph/__init__.py
blif2graph/__main__.py
blif2graph/_version.py
blif2graph/blif2graph.py
blif2graph/fsm2graph.py
blif2graph/lgate2graph.py
blif2graph/utility.py
blif2graph-1.0.0.dist-info/LICENSE.txt
blif2graph-1.0.0.dist-info/METADATA
blif2graph-1.0.0.dist-info/WHEEL
blif2graph-1.0.0.dist-info/entry_points.txt
blif2graph-1.0.0.dist-info/top_level.txt
blif2graph-1.0.0.dist-info/RECORD
