Metadata-Version: 2.1
Name: blif2graph
Version: 1.0.0
Summary: Generate graphs from BLIF files
Home-page: https://github.com/mario33881/blif2graph
Author: Zenaro Stefano (mario33881)
Author-email: mariortgasd@hotmail.com
License: MIT
Keywords: SIS BLIF Graph
Platform: UNKNOWN
Classifier: Development Status :: 5 - Production/Stable
Classifier: License :: OSI Approved :: MIT License
Classifier: Programming Language :: Python :: 3
Requires-Python: >=3
License-File: LICENSE.txt
Requires-Dist: graphviz (==0.17)
Requires-Dist: blifparser (==1.0.0)
